insanonym_utils/F_user_7_0d54717e83a17d6eb39491c4a3f9eaa27a776572b769f9c7af6c23195f70fa6c
insanonym_utils/__init__.py
insanonym_utils/algorithms.py
insanonym_utils/models.py
insanonym_utils/runner.py
insanonym_utils/utils.py
insanonym_utils-0.10.5.dist-info/entry_points.txt
insanonym_utils-0.10.5.dist-info/LICENSE
insanonym_utils-0.10.5.dist-info/WHEEL
insanonym_utils-0.10.5.dist-info/METADATA
insanonym_utils-0.10.5.dist-info/RECORD
